ps2mc/__init__.py
ps2mc/browser.py
ps2mc/ecc.py
ps2mc/error.py
ps2mc/icon.py
ps2mc/ps2mc.py
ps2mc/utils.py
ps2mc-0.1.1.dist-info/METADATA
ps2mc-0.1.1.dist-info/WHEEL
ps2mc-0.1.1.dist-info/licenses/LICENSE
ps2mc-0.1.1.dist-info/RECORD
